mlgrad/__init__.pxd
mlgrad/__init__.py
mlgrad/_linalg.cp312-win_amd64.pyd
mlgrad/_linalg.pxd
mlgrad/array_allocator.cp312-win_amd64.pyd
mlgrad/array_allocator.pxd
mlgrad/array_transform.pxd
mlgrad/averager.cp312-win_amd64.pyd
mlgrad/averager.pxd
mlgrad/avragg.cp312-win_amd64.pyd
mlgrad/avragg.pxd
mlgrad/batch.cp312-win_amd64.pyd
mlgrad/batch.pxd
mlgrad/dissimilarity.cp312-win_amd64.pyd
mlgrad/dissimilarity.pxd
mlgrad/distance.cp312-win_amd64.pyd
mlgrad/distance.pxd
mlgrad/distrfuncs.pxd
mlgrad/funcs.cp312-win_amd64.pyd
mlgrad/funcs.pxd
mlgrad/funcs2.cp312-win_amd64.pyd
mlgrad/funcs2.pxd
mlgrad/gd.cp312-win_amd64.pyd
mlgrad/gd.pxd
mlgrad/inventory.cp312-win_amd64.pyd
mlgrad/inventory.pxd
mlgrad/irgd.py
mlgrad/kaverage.cp312-win_amd64.pyd
mlgrad/kaverage.pxd
mlgrad/kmeans.cp312-win_amd64.pyd
mlgrad/kmeans.pxd
mlgrad/kmeans_mlocation_scatter.pxd
mlgrad/list_values.cp312-win_amd64.pyd
mlgrad/list_values.pxd
mlgrad/loss.cp312-win_amd64.pyd
mlgrad/loss.pxd
mlgrad/ls4linear.pxd
mlgrad/miscfuncs.pxd
mlgrad/mlocation_scatter.pxd
mlgrad/mlocation_scatter2.cp312-win_amd64.pyd
mlgrad/mlocation_scatter2.pxd
mlgrad/models.cp312-win_amd64.pyd
mlgrad/models.pxd
mlgrad/normalizer.pxd
mlgrad/paramrate.pxd
mlgrad/risks.cp312-win_amd64.pyd
mlgrad/risks.pxd
mlgrad/utils.py
mlgrad/weights.cp312-win_amd64.pyd
mlgrad/weights.pxd
mlgrad/af/__init__.py
mlgrad/boost/__init__.py
mlgrad/boost/gb_classification.py
mlgrad/boost/gb_regression.py
mlgrad/cls/__init__.py
mlgrad/cls/cls_pca.py
mlgrad/cls/margin_max.py
mlgrad/cluster/__init__.py
mlgrad/cluster/kmeans.py
mlgrad/cluster/mixture.py
mlgrad/outl/__init__.py
mlgrad/pca/__init__.py
mlgrad/pca/_pca.cp312-win_amd64.pyd
mlgrad/pca/_pca.pxd
mlgrad/pca/location_scatter.py
mlgrad/pca/pca.py
mlgrad/plots/__init__.py
mlgrad/regr/__init__.py
mlgrad/regr/irls.py
mlgrad/regr/rbf_regression.py
mlgrad/smooth/__init__.py
mlgrad/smooth/_whittaker.cp312-win_amd64.pyd
mlgrad/smooth/_whittaker.pxd
mlgrad/smooth/whittaker.py
mlgrad/test/__init__.py
mlgrad-0.7.3.dist-info/licenses/licence.txt
mlgrad-0.7.3.dist-info/METADATA
mlgrad-0.7.3.dist-info/WHEEL
mlgrad-0.7.3.dist-info/top_level.txt
mlgrad-0.7.3.dist-info/RECORD
